simpletextprogressbar/__init__.py
simpletextprogressbar-1.1.2.dist-info/LICENSE
simpletextprogressbar-1.1.2.dist-info/METADATA
simpletextprogressbar-1.1.2.dist-info/WHEEL
simpletextprogressbar-1.1.2.dist-info/top_level.txt
simpletextprogressbar-1.1.2.dist-info/RECORD
