Metadata-Version: 2.1
Name: simpletextprogressbar
Version: 1.1.2
Summary: A simple progress bar for simple projects
Home-page: https://github.com/Inky1003/SimpleTextProgressBar/
Author: Inky
Author-email: inky1003@gmail.com
License: UNKNOWN
Project-URL: Bug Reports, https://github.com/Inky1003/SimpleTextProgressBar/issues
Project-URL: Source, https://github.com/Inky1003/SimpleTextProgressBar/
Keywords: progress bar command line console text window simple lightweight
Platform: UNKNOWN
Classifier: Programming Language :: Python :: 3
Classifier: License :: OSI Approved :: GNU General Public License v3 (GPLv3)
Classifier: Operating System :: OS Independent
Requires-Python: >=3.5
